zeroros/__init__.py
zeroros/datalogger.py
zeroros/message_broker.py
zeroros/publisher.py
zeroros/rate.py
zeroros/subscriber.py
zeroros/timer.py
zeroros/topic.py
zeroros/messages/__init__.py
zeroros/messages/geometry_msgs.py
zeroros/messages/nav_msgs.py
zeroros/messages/range_bearing_msgs.py
zeroros/messages/sensor_msgs.py
zeroros/messages/std_msgs.py
zeroros-1.1.1.dist-info/licenses/LICENSE
zeroros-1.1.1.dist-info/METADATA
zeroros-1.1.1.dist-info/WHEEL
zeroros-1.1.1.dist-info/top_level.txt
zeroros-1.1.1.dist-info/RECORD
