Metadata-Version: 2.4
Name: zeroros
Version: 1.1.1
Summary: ZeroROS middleware
Home-page: https://github.com/miquelmassot/zeroros
Author: Miquel Massot
Author-email: miquel.massot@gmail.com
Maintainer: Miquel Massot; Blair Thornton
Maintainer-email: miquel.massot@gmail.com; b.thornton@soton.ac.uk
License: BSD-3-Clause
Project-URL: Bug Reports, https://github.com/miquelmassot/zeroros/issues
Project-URL: Source, https://github.com/miquelmassot/zeroros
Classifier: Development Status :: 4 - Beta
Classifier: Intended Audience :: Developers
Classifier: Intended Audience :: Science/Research
Classifier: License :: OSI Approved :: BSD License
Classifier: Programming Language :: Python :: 3
Classifier: Topic :: Software Development
Classifier: Topic :: Software Development :: Libraries
Classifier: Topic :: Software Development :: Libraries :: Python Modules
License-File: LICENSE
Requires-Dist: numpy>=1.23.4
Requires-Dist: pyzmq>=24.0.1
Requires-Dist: setuptools>=59.6.0
Dynamic: author
Dynamic: author-email
Dynamic: classifier
Dynamic: description
Dynamic: description-content-type
Dynamic: home-page
Dynamic: license
Dynamic: license-file
Dynamic: maintainer
Dynamic: maintainer-email
Dynamic: project-url
Dynamic: requires-dist
Dynamic: summary
